isalt-2021.2.2-py3.9-nspkg.pth
isalt/scripts.py
isalt-2021.2.2.data/data/man/man1/isalt.1
isalt-2021.2.2.dist-info/LICENSE
isalt-2021.2.2.dist-info/METADATA
isalt-2021.2.2.dist-info/WHEEL
isalt-2021.2.2.dist-info/entry_points.txt
isalt-2021.2.2.dist-info/namespace_packages.txt
isalt-2021.2.2.dist-info/top_level.txt
isalt-2021.2.2.dist-info/RECORD
