Metadata-Version: 2.1
Name: isalt
Version: 2021.2.2
Summary: ISalt: Interactive Salt Programming
Home-page: https://github.com/mirceaulinic/isalt
Author: Mircea Ulinic
Author-email: ping@mirceaulinic.net
License: Apache License 2.0
Keywords: Salt, Interactive, Interpreter,Shell,Embedding
Platform: UNKNOWN
Classifier: Development Status :: 5 - Production/Stable
Classifier: Environment :: Console
Classifier: License :: OSI Approved :: Apache Software License
Classifier: Topic :: Utilities
Classifier: Topic :: System :: Shells
Classifier: Topic :: System :: Systems Administration
Classifier: Framework :: IPython
Classifier: Programming Language :: Python
Classifier: Programming Language :: Cython
Classifier: Programming Language :: Python :: 3
Classifier: Programming Language :: Python :: 3.6
Classifier: Programming Language :: Python :: 3.7
Classifier: Programming Language :: Python :: 3.8
Classifier: Operating System :: POSIX
Classifier: Operating System :: Microsoft :: Windows
Classifier: Operating System :: MacOS
Classifier: Intended Audience :: Developers
Classifier: Intended Audience :: System Administrators
Classifier: Intended Audience :: Education
Classifier: Intended Audience :: Science/Research
Requires-Dist: salt
Requires-Dist: ipython
Provides-Extra: sproxy
Requires-Dist: salt-sproxy ; extra == 'sproxy'
